duckpte/__init__.py
duckpte/connection_manager.py
duckpte/engine.py
duckpte/peewee_backend.py
duckpte/py.typed
duckpte/transaction.py
duckpte-0.1.0.dist-info/METADATA
duckpte-0.1.0.dist-info/WHEEL
duckpte-0.1.0.dist-info/top_level.txt
duckpte-0.1.0.dist-info/RECORD
