Metadata-Version: 2.4
Name: duckpte
Version: 0.1.0
Summary: DuckDB Parallel Transaction Engine - модуль для работы с DuckDB с поддержкой транзакций, конкурентных операций и Peewee ORM
Author: Developer
Project-URL: Homepage, https://github.com/developer/duckpte
Project-URL: Documentation, https://github.com/developer/duckpte#readme
Project-URL: Repository, https://github.com/developer/duckpte
Project-URL: Issues, https://github.com/developer/duckpte/issues
Keywords: duckdb,database,transactions,concurrent,parallel,sql,analytics,peewee,orm
Classifier: Development Status :: 4 - Beta
Classifier: Intended Audience :: Developers
Classifier: License :: OSI Approved :: MIT License
Classifier: Operating System :: OS Independent
Classifier: Programming Language :: Python :: 3
Classifier: Programming Language :: Python :: 3.8
Classifier: Programming Language :: Python :: 3.9
Classifier: Programming Language :: Python :: 3.10
Classifier: Programming Language :: Python :: 3.11
Classifier: Programming Language :: Python :: 3.12
Classifier: Topic :: Database
Classifier: Topic :: Database :: Front-Ends
Classifier: Topic :: Software Development :: Libraries :: Python Modules
Requires-Python: >=3.8
Requires-Dist: duckdb>=0.9.0
Requires-Dist: peewee>=3.16.0
Provides-Extra: pandas
Requires-Dist: pandas>=2.0.0; extra == "pandas"
Provides-Extra: dev
Requires-Dist: pytest>=7.0.0; extra == "dev"
Requires-Dist: pytest-cov>=4.0.0; extra == "dev"
Requires-Dist: black>=23.0.0; extra == "dev"
Requires-Dist: mypy>=1.0.0; extra == "dev"
Requires-Dist: ruff>=0.1.0; extra == "dev"
Provides-Extra: all
Requires-Dist: duckpte[dev,pandas]; extra == "all"
